{
  "culture": "hi",
  "texts": {
    "Menu:Home": "घर",
    "Welcome": "स्वागत हे",
    "LongWelcomeMessage": "आवेदन करने के लिए आपका स्वागत है। यह एबीपी ढांचे पर आधारित एक स्टार्टअप परियोजना है। अधिक जानकारी के लिए, abp.io पर जाएं।",
    "Permission:DealCategory": "DealCategory",
    "Permission:Create": "Create",
    "Permission:Update": "Update",
    "Permission:Delete": "Delete",
    "Menu:DealCategory": "MenuDealCategory",
    "DealCategory": "DealCategory",
    "DealCategoryName": "DealCategoryName",
    "DealCategoryDescription": "DealCategoryDescription",
    "DealCategoryPublishDate": "DealCategoryPublishDate",
    "DealCategoryModifiedDate": "DealCategoryModifiedDate",
    "CreateDealCategory": "CreateDealCategory",
    "EditDealCategory": "EditDealCategory",
    "DealCategoryDeletionConfirmationMessage": "Are you sure to delete the dealCategory {0}?",
    "SuccessfullyDeleted": "Successfully deleted",
    "DealCategoryCatOrder": "DealCategoryCatOrder",
    "Permission:Deal": "Deal",
    "Menu:Deal": "MenuDeal",
    "Deal": "Deal",
    "DealTitle": "DealTitle",
    "DealDescription": "DealDescription",
    "DealDealCategoryId": "DealDealCategoryId",
    "DealDealPriority": "DealDealPriority",
    "DealPrice": "DealPrice",
    "DealPricePromo": "DealPricePromo",
    "DealFreeShipping": "DealFreeShipping",
    "DealPriceShipping": "DealPriceShipping",
    "DealCodePromo": "DealCodePromo",
    "DealBeginPromo": "DealBeginPromo",
    "DealEndPromo": "DealEndPromo",
    "DealCityId": "DealCityId",
    "DealLocalShop": "DealLocalShop",
    "DealPublishDate": "DealPublishDate",
    "DealModifiedDate": "DealModifiedDate",
    "CreateDeal": "CreateDeal",
    "EditDeal": "EditDeal",
    "DealDeletionConfirmationMessage": "Are you sure to delete the deal {0}?",
    "DealLink": "DealLink",
    "DealDomainLink": "DealDomainLink",
    "DealImage": "DealImage",
    "DealCity": "DealCity",
    "DealCategoryParent": "DealCategoryParent",
    "Permission:Country": "Country",
    "Menu:Country": "MenuCountry",
    "Country": "Country",
    "CountryName": "CountryName",
    "CountryFlag": "CountryFlag",
    "CountryOrderCountry": "CountryOrderCountry",
    "CreateCountry": "CreateCountry",
    "EditCountry": "EditCountry",
    "CountryDeletionConfirmationMessage": "Are you sure to delete the country {0}?",
    "Permission:City": "City",
    "Menu:City": "MenuCity",
    "City": "City",
    "CityCountryId": "CityCountryId",
    "CityName": "CityName",
    "CityOrderCity": "CityOrderCity",
    "CreateCity": "CreateCity",
    "EditCity": "EditCity",
    "CityDeletionConfirmationMessage": "Are you sure to delete the city {0}?"
  }
}